gentem/__init__.py
gentem/__main__.py
gentem/cli.py
gentem/template_engine.py
gentem/commands/__init__.py
gentem/commands/fastapi.py
gentem/commands/init.py
gentem/commands/new.py
gentem/utils/__init__.py
gentem/utils/validators.py
gentem-0.2.0.dist-info/licenses/LICENSE
gentem-0.2.0.dist-info/METADATA
gentem-0.2.0.dist-info/WHEEL
gentem-0.2.0.dist-info/entry_points.txt
gentem-0.2.0.dist-info/top_level.txt
gentem-0.2.0.dist-info/RECORD
