Metadata-Version: 2.4
Name: gentem
Version: 0.2.0
Summary: Python CLI template boilerplate generator
Author-email: Abu Bakr <mabs2406@gmail.com>
License: MIT
Keywords: cli,boilerplate,template,generator,scaffolding
Classifier: Development Status :: 3 - Alpha
Classifier: Environment :: Console
Classifier: Intended Audience :: Developers
Classifier: License :: OSI Approved :: MIT License
Classifier: Programming Language :: Python :: 3
Classifier: Programming Language :: Python :: 3.9
Classifier: Programming Language :: Python :: 3.10
Classifier: Programming Language :: Python :: 3.11
Classifier: Programming Language :: Python :: 3.12
Requires-Python: >=3.9
License-File: LICENSE
Requires-Dist: typer>=0.9.0
Requires-Dist: jinja2>=3.1.0
Requires-Dist: rich>=13.0.0
Requires-Dist: questionary>=2.0.0
Provides-Extra: dev
Requires-Dist: pytest>=7.4.0; extra == "dev"
Requires-Dist: pytest-cov>=4.1.0; extra == "dev"
Requires-Dist: black>=23.0.0; extra == "dev"
Requires-Dist: ruff>=0.1.0; extra == "dev"
Requires-Dist: mypy>=1.5.0; extra == "dev"
Requires-Dist: types-pyyaml>=6.0.0; extra == "dev"
Dynamic: license-file
